{
    "id": 3,
    "world_id": "supermarket",
    "name": "level_003",
    "star_move_thresholds": [
        6,
        7,
        8,
        9
    ],
    "time_limit_seconds": 0,
    "construction_moves": 0,
    "containers": [
        {
            "id": "train_top_1",
            "position": {
                "x": -150.0,
                "y": 350.0
            },
            "container_type": "standard",
            "container_image": "supermarket_container",
            "slot_count": 3,
            "max_rows_per_slot": 1,
            "is_locked": false,
            "unlock_matches_required": 0,
            "lock_overlay_image": "",
            "unlock_animation": "",
            "is_moving": true,
            "move_type": "carousel",
            "move_direction": "right",
            "move_speed": 80.0,
            "move_distance": 1485.0,
            "track_id": "",
            "is_falling": false,
            "fall_speed": 100.0,
            "fall_target_y": 0.0,
            "despawn_on_match": false,
            "initial_items": [
                {
                    "id": "orangejuice",
                    "row": 0,
                    "slot": 0
                },
                {
                    "id": "orangejuice",
                    "row": 0,
                    "slot": 1
                }
            ]
        },
        {
            "id": "train_top_2",
            "position": {
                "x": 147.0,
                "y": 350.0
            },
            "container_type": "standard",
            "container_image": "supermarket_container",
            "slot_count": 3,
            "max_rows_per_slot": 1,
            "is_locked": true,
            "unlock_matches_required": 2,
            "lock_overlay_image": "supermarket_lockoverlay",
            "unlock_animation": "",
            "is_moving": true,
            "move_type": "carousel",
            "move_direction": "right",
            "move_speed": 80.0,
            "move_distance": 1485.0,
            "track_id": "",
            "is_falling": false,
            "fall_speed": 100.0,
            "fall_target_y": 0.0,
            "despawn_on_match": false,
            "initial_items": [
                {
                    "id": "grapesoda",
                    "row": 0,
                    "slot": 0
                },
                {
                    "id": "grapesoda",
                    "row": 0,
                    "slot": 1
                },
                {
                    "id": "chocolatebar",
                    "row": 0,
                    "slot": 2
                }
            ]
        },
        {
            "id": "train_top_3",
            "position": {
                "x": 444.0,
                "y": 350.0
            },
            "container_type": "standard",
            "container_image": "supermarket_container",
            "slot_count": 3,
            "max_rows_per_slot": 1,
            "is_locked": false,
            "unlock_matches_required": 0,
            "lock_overlay_image": "",
            "unlock_animation": "",
            "is_moving": true,
            "move_type": "carousel",
            "move_direction": "right",
            "move_speed": 80.0,
            "move_distance": 1485.0,
            "track_id": "",
            "is_falling": false,
            "fall_speed": 100.0,
            "fall_target_y": 0.0,
            "despawn_on_match": false,
            "initial_items": [
                {
                    "id": "orangejuice",
                    "row": 0,
                    "slot": 0
                },
                {
                    "id": "pickles",
                    "row": 0,
                    "slot": 1
                },
                {
                    "id": "pickles",
                    "row": 0,
                    "slot": 2
                }
            ]
        },
        {
            "id": "train_top_4",
            "position": {
                "x": 741.0,
                "y": 350.0
            },
            "container_type": "standard",
            "container_image": "supermarket_container",
            "slot_count": 3,
            "max_rows_per_slot": 1,
            "is_locked": false,
            "unlock_matches_required": 0,
            "lock_overlay_image": "",
            "unlock_animation": "",
            "is_moving": true,
            "move_type": "carousel",
            "move_direction": "right",
            "move_speed": 80.0,
            "move_distance": 1485.0,
            "track_id": "",
            "is_falling": false,
            "fall_speed": 100.0,
            "fall_target_y": 0.0,
            "despawn_on_match": false,
            "initial_items": [
                {
                    "id": "pickles",
                    "row": 0,
                    "slot": 0
                },
                {
                    "id": "peanutbutter",
                    "row": 0,
                    "slot": 1
                }
            ]
        },
        {
            "id": "train_top_5",
            "position": {
                "x": 1038.0,
                "y": 350.0
            },
            "container_type": "standard",
            "container_image": "supermarket_container",
            "slot_count": 3,
            "max_rows_per_slot": 1,
            "is_locked": false,
            "unlock_matches_required": 0,
            "lock_overlay_image": "",
            "unlock_animation": "",
            "is_moving": true,
            "move_type": "carousel",
            "move_direction": "right",
            "move_speed": 80.0,
            "move_distance": 1485.0,
            "track_id": "",
            "is_falling": false,
            "fall_speed": 100.0,
            "fall_target_y": 0.0,
            "despawn_on_match": false,
            "initial_items": []
        },
        {
            "id": "train_bottom_1",
            "position": {
                "x": 1185.0,
                "y": 650.0
            },
            "container_type": "standard",
            "container_image": "supermarket_container",
            "slot_count": 3,
            "max_rows_per_slot": 1,
            "is_locked": false,
            "unlock_matches_required": 0,
            "lock_overlay_image": "",
            "unlock_animation": "",
            "is_moving": true,
            "move_type": "carousel",
            "move_direction": "left",
            "move_speed": 80.0,
            "move_distance": 1485.0,
            "track_id": "",
            "is_falling": false,
            "fall_speed": 100.0,
            "fall_target_y": 0.0,
            "despawn_on_match": false,
            "initial_items": [
                {
                    "id": "peanutbutter",
                    "row": 0,
                    "slot": 0
                },
                {
                    "id": "peanutbutter",
                    "row": 0,
                    "slot": 1
                }
            ]
        },
        {
            "id": "train_bottom_2",
            "position": {
                "x": 888.0,
                "y": 650.0
            },
            "container_type": "standard",
            "container_image": "supermarket_container",
            "slot_count": 3,
            "max_rows_per_slot": 1,
            "is_locked": true,
            "unlock_matches_required": 2,
            "lock_overlay_image": "supermarket_lockoverlay",
            "unlock_animation": "",
            "is_moving": true,
            "move_type": "carousel",
            "move_direction": "left",
            "move_speed": 80.0,
            "move_distance": 1485.0,
            "track_id": "",
            "is_falling": false,
            "fall_speed": 100.0,
            "fall_target_y": 0.0,
            "despawn_on_match": false,
            "initial_items": [
                {
                    "id": "chocolatebar",
                    "row": 0,
                    "slot": 0
                },
                {
                    "id": "chocolatebar",
                    "row": 0,
                    "slot": 1
                }
            ]
        },
        {
            "id": "train_bottom_3",
            "position": {
                "x": 591.0,
                "y": 650.0
            },
            "container_type": "standard",
            "container_image": "supermarket_container",
            "slot_count": 3,
            "max_rows_per_slot": 1,
            "is_locked": false,
            "unlock_matches_required": 0,
            "lock_overlay_image": "",
            "unlock_animation": "",
            "is_moving": true,
            "move_type": "carousel",
            "move_direction": "left",
            "move_speed": 80.0,
            "move_distance": 1485.0,
            "track_id": "",
            "is_falling": false,
            "fall_speed": 100.0,
            "fall_target_y": 0.0,
            "despawn_on_match": false,
            "initial_items": [
                {
                    "id": "mayo",
                    "row": 0,
                    "slot": 0
                },
                {
                    "id": "mayo",
                    "row": 0,
                    "slot": 1
                }
            ]
        },
        {
            "id": "train_bottom_4",
            "position": {
                "x": 294.0,
                "y": 650.0
            },
            "container_type": "standard",
            "container_image": "supermarket_container",
            "slot_count": 3,
            "max_rows_per_slot": 1,
            "is_locked": false,
            "unlock_matches_required": 0,
            "lock_overlay_image": "",
            "unlock_animation": "",
            "is_moving": true,
            "move_type": "carousel",
            "move_direction": "left",
            "move_speed": 80.0,
            "move_distance": 1485.0,
            "track_id": "",
            "is_falling": false,
            "fall_speed": 100.0,
            "fall_target_y": 0.0,
            "despawn_on_match": false,
            "initial_items": [
                {
                    "id": "mayo",
                    "row": 0,
                    "slot": 0
                },
                {
                    "id": "grapesoda",
                    "row": 0,
                    "slot": 1
                }
            ]
        },
        {
            "id": "train_bottom_5",
            "position": {
                "x": -3.0,
                "y": 650.0
            },
            "container_type": "standard",
            "container_image": "supermarket_container",
            "slot_count": 3,
            "max_rows_per_slot": 1,
            "is_locked": false,
            "unlock_matches_required": 0,
            "lock_overlay_image": "",
            "unlock_animation": "",
            "is_moving": true,
            "move_type": "carousel",
            "move_direction": "left",
            "move_speed": 80.0,
            "move_distance": 1485.0,
            "track_id": "",
            "is_falling": false,
            "fall_speed": 100.0,
            "fall_target_y": 0.0,
            "despawn_on_match": false,
            "initial_items": []
        }
    ],
    "moving_tracks": []
}